Sorting_modules/Insertion_Sort/Insertion_Sort.srcs/sources_1/new/insertion_sort.v
`timescale 1ns / 1ps

module insertion_sort #(
    parameter N = 8,
    parameter WIDTH = 8
)(
    input  wire                 clk,
    input  wire                 rst,
    input  wire                 data_valid,     // ONLY trigger to start sorting
    input  wire [N*WIDTH-1:0]   data_in,
    output reg  [N*WIDTH-1:0]   sorted,
    output reg                  sdone
);

    reg [WIDTH-1:0] arr [0:N-1];
    reg [WIDTH-1:0] key;
    integer i, j;

    localparam
        IDLE    = 3'b000,
        LOAD    = 3'b001,
        PICK    = 3'b010,
        COMPARE = 3'b011,
        INSERT  = 3'b100,
        FINISH  = 3'b101;

    reg [2:0] state;

    always @(posedge clk or posedge rst) begin
        if (rst) begin
            state  <= IDLE;
            sdone  <= 0;
            i      <= 0;
            j      <= 0;
            key    <= 0;
            sorted <= 0;
        end
        else begin
            case (state)

                IDLE: begin
                    sdone <= 0;
                    if (data_valid) begin
                        for (i = 0; i < N; i = i + 1)
                            arr[i] <= data_in[i*WIDTH +: WIDTH];
                        i <= 1;
                        state <= PICK;
                    end
                end

                PICK: begin
                    if (i < N) begin
                        key <= arr[i];
                        j   <= i - 1;
                        state <= COMPARE;
                    end else begin
                        state <= FINISH;
                    end
                end

                COMPARE: begin
                    if (j >= 0 && arr[j] > key) begin
                        arr[j+1] <= arr[j];
                        j <= j - 1;
                    end
                    else begin
                        state <= INSERT;
                    end
                end

                INSERT: begin
                    arr[j+1] <= key;
                    i <= i + 1;
                    state <= PICK;
                end

                FINISH: begin
                    for (j = 0; j < N; j = j + 1)
                        sorted[j*WIDTH +: WIDTH] <= arr[j];
                    sdone <= 1;
                    state <= IDLE;
                end

            endcase
        end
    end

endmodule

Asynchronous FIFO/Asynchronous FIFO.srcs/sources_1/new/async_fifo.v
`timescale 1ns / 1ps

module async_fifo #(
    parameter DATA_WIDTH = 64,
    parameter ADDR_WIDTH = 3
)(
    input  wire                   wr_clk,
    input  wire                   rd_clk,
    input  wire                   rst,
    input  wire [DATA_WIDTH-1:0]  din,
    input  wire                   wr_en,
    input  wire                   rd_en,
    output wire [DATA_WIDTH-1:0]  dout,
    output wire                   full,
    output wire                   empty
);

    localparam PTR_WIDTH = ADDR_WIDTH + 1;
    reg [DATA_WIDTH-1:0] mem [0:(1<<ADDR_WIDTH)-1];

    reg [PTR_WIDTH-1:0] wr_ptr_bin, wr_ptr_bin_next;
    reg [PTR_WIDTH-1:0] wr_ptr_gray, wr_ptr_gray_next;
    wire [ADDR_WIDTH-1:0] wr_addr = wr_ptr_bin[ADDR_WIDTH-1:0];

    reg [PTR_WIDTH-1:0] rd_ptr_bin, rd_ptr_bin_next;
    reg [PTR_WIDTH-1:0] rd_ptr_gray, rd_ptr_gray_next;
    wire [ADDR_WIDTH-1:0] rd_addr = rd_ptr_bin[ADDR_WIDTH-1:0];

    reg [PTR_WIDTH-1:0] rd_ptr_gray_sync1, rd_ptr_gray_sync2;
    always @(posedge wr_clk or posedge rst) begin
        if (rst) begin
            rd_ptr_gray_sync1 <= 0;
            rd_ptr_gray_sync2 <= 0;
        end else begin
            rd_ptr_gray_sync1 <= rd_ptr_gray;
            rd_ptr_gray_sync2 <= rd_ptr_gray_sync1;
        end
    end

    reg [PTR_WIDTH-1:0] wr_ptr_gray_sync1, wr_ptr_gray_sync2;
    always @(posedge rd_clk or posedge rst) begin
        if (rst) begin
            wr_ptr_gray_sync1 <= 0;
            wr_ptr_gray_sync2 <= 0;
        end else begin
            wr_ptr_gray_sync1 <= wr_ptr_gray;
            wr_ptr_gray_sync2 <= wr_ptr_gray_sync1;
        end
    end

    function [PTR_WIDTH-1:0] gray_to_bin;
        input [PTR_WIDTH-1:0] g;
        integer i;
        begin
            gray_to_bin[PTR_WIDTH-1] = g[PTR_WIDTH-1];
            for (i = PTR_WIDTH-2; i >= 0; i = i - 1)
                gray_to_bin[i] = gray_to_bin[i+1] ^ g[i];
        end
    endfunction

    wire [PTR_WIDTH-1:0] rd_ptr_bin_sync = gray_to_bin(rd_ptr_gray_sync2);
    assign full = (wr_ptr_gray_next == {~rd_ptr_gray_sync2[PTR_WIDTH-1:PTR_WIDTH-2], rd_ptr_gray_sync2[PTR_WIDTH-3:0]});

    wire [PTR_WIDTH-1:0] wr_ptr_bin_sync = gray_to_bin(wr_ptr_gray_sync2);
    assign empty = (rd_ptr_gray == wr_ptr_gray_sync2);

    always @(*) begin
        wr_ptr_bin_next = wr_ptr_bin;
        if (wr_en && !full)
            wr_ptr_bin_next = wr_ptr_bin + 1'b1;
        wr_ptr_gray_next = (wr_ptr_bin_next >> 1) ^ wr_ptr_bin_next;
    end

    always @(posedge wr_clk or posedge rst) begin
        if (rst) begin
            wr_ptr_bin <= 0;
            wr_ptr_gray <= 0;
        end else begin
            wr_ptr_bin <= wr_ptr_bin_next;
            wr_ptr_gray <= wr_ptr_gray_next;
        end
    end

    always @(posedge wr_clk) begin
        if (wr_en && !full)
            mem[wr_addr] <= din;
    end

    reg [DATA_WIDTH-1:0] dout_reg;
    always @(posedge rd_clk) begin
        if (rd_en && !empty)
            dout_reg <= mem[rd_addr];
    end
    assign dout = dout_reg;

    always @(*) begin
        rd_ptr_bin_next = rd_ptr_bin;
        if (rd_en && !empty)
            rd_ptr_bin_next = rd_ptr_bin + 1'b1;
        rd_ptr_gray_next = (rd_ptr_bin_next >> 1) ^ rd_ptr_bin_next;
    end

    always @(posedge rd_clk or posedge rst) begin
        if (rst) begin
            rd_ptr_bin <= 0;
            rd_ptr_gray <= 0;
        end else begin
            rd_ptr_bin <= rd_ptr_bin_next;
            rd_ptr_gray <= rd_ptr_gray_next;
        end
    end

endmodule

Random_num_generator/Random_num_generator.srcs/sources_1/new/random_gen.v
`timescale 1ns / 1ps

module random_gen(
    input  wire        clk,
    input  wire        rst,
    output reg  [63:0] rnd64,
    output reg         valid64
);

    reg  [7:0] lfsr_byte;
    wire [7:0] lfsr_byte_next;
    wire       fb_byte;
    assign fb_byte = lfsr_byte[7] ^ lfsr_byte[5] ^ lfsr_byte[4] ^ lfsr_byte[3];
    assign lfsr_byte_next = { lfsr_byte[6:0], fb_byte };

    reg  [7:0] dlfsr;
    wire [7:0] dlfsr_next;
    assign dlfsr_next = { dlfsr[6:0], dlfsr[7] ^ dlfsr[5] ^ dlfsr[3] ^ dlfsr[2] };

    reg  [4:0] delay_val;
    reg [7:0] byte_array [0:6];
    reg [2:0] byte_index;
    reg [4:0] delay_cnt;

    wire sample_enable = (delay_cnt == 5'd0);

    always @(posedge clk) begin
        if (rst) begin
            lfsr_byte <= 8'h01;
            dlfsr     <= 8'hA5;
            delay_val <= 5'd4;
        end
        else begin
            if (sample_enable) begin
                dlfsr <= dlfsr_next;
                lfsr_byte <= lfsr_byte_next;
                if ((dlfsr_next[3:0] ^ dlfsr_next[7:4]) == 4'd0)
                    delay_val <= 5'd8;
                else
                    delay_val <= {1'b0, (dlfsr_next[3:0] ^ dlfsr_next[7:4])};
            end
        end
    end

    always @(posedge clk) begin
        if (rst) begin
            byte_index <= 3'd0;
            delay_cnt  <= 5'd1;
            rnd64      <= 64'd0;
            valid64    <= 1'b0;
        end
        else begin
            valid64 <= 1'b0;
            if (delay_cnt == 5'd0) begin
                if (byte_index == 3'd7) begin
                    rnd64 <= {
                        lfsr_byte,
                        byte_array[6],
                        byte_array[5],
                        byte_array[4],
                        byte_array[3],
                        byte_array[2],
                        byte_array[1],
                        byte_array[0]
                    };
                    valid64 <= 1'b1;
                    byte_index <= 3'd0;
                end
                else begin
                    byte_array[byte_index] <= lfsr_byte;
                    byte_index <= byte_index + 3'd1;
                end

                if (delay_val < 2)
                    delay_cnt <= 5'd1;
                else
                    delay_cnt <= delay_val - 5'd1;
            end
            else begin
                delay_cnt <= delay_cnt - 5'd1;
            end
        end
    end

endmodule

Testing_folder/Testing_folder.srcs/sources_1/new/top_random_fifo.v
`timescale 1ns / 1ps

module top_random_fifo (
    input  wire        wr_clk,
    input  wire        rd_clk,
    input  wire        rst,
    input  wire        rd_en,
    output wire [63:0] fifo_dout,
    output wire        fifo_empty,
    output wire        fifo_full,
    output wire        drop
);

    wire [63:0] rnd64;
    wire        valid64;
    reg         wr_en;
    wire [63:0] din;
    reg         drop_r;

    random_gen u_random (
        .clk(wr_clk),
        .rst(rst),
        .rnd64(rnd64),
        .valid64(valid64)
    );

    assign din = rnd64;

    always @(posedge wr_clk or posedge rst) begin
        if (rst) begin
            wr_en <= 1'b0;
            drop_r <= 1'b0;
        end
        else begin
            drop_r <= 1'b0;
            if (valid64) begin
                if (!fifo_full) begin
                    wr_en <= 1'b1;
                end
                else begin
                    wr_en <= 1'b0;
                    drop_r <= 1'b1;
                end
            end
            else begin
                wr_en <= 1'b0;
            end
        end
    end

    async_fifo #(
        .DATA_WIDTH(64),
        .ADDR_WIDTH(3)
    ) u_fifo (
        .wr_clk(wr_clk),
        .rd_clk(rd_clk),
        .rst(rst),
        .din(din),
        .wr_en(wr_en),
        .rd_en(rd_en),
        .dout(fifo_dout),
        .full(fifo_full),
        .empty(fifo_empty)
    );

    assign drop = drop_r;

endmodule

Testing_folder/Testing_folder.srcs/sources_1/new/top_rand_fifo_sort.v
`timescale 1ns / 1ps

module top_rand_fifo_sort(
    input  wire        wr_clk,
    input  wire        rd_clk,
    input  wire        reset,
    output reg  [63:0] sort_out,
    output reg         done
);

    reg                 rd_en;
    wire [63:0]         fifo_out;
    wire                fifo_empty;
    wire                fifo_full;
    wire                drop;

    top_random_fifo u_top_random_fifo (
        .wr_clk    (wr_clk),
        .rd_clk    (rd_clk),
        .rst       (reset),
        .rd_en     (rd_en),
        .fifo_dout (fifo_out),
        .fifo_empty(fifo_empty),
        .fifo_full (fifo_full),
        .drop      (drop)
    );

    localparam N = 8;
    localparam WIDTH = 8;

    reg  [N*WIDTH-1:0] sorter_data_in;
    reg                sorter_data_valid;
    wire [N*WIDTH-1:0] sorter_sorted;
    wire               sorter_sdone;

    insertion_sort #(
        .N(N),
        .WIDTH(WIDTH)
    ) u_insertion_sort (
        .clk        (rd_clk),
        .rst        (reset),
        .data_valid (sorter_data_valid),
        .data_in    (sorter_data_in),
        .sorted     (sorter_sorted),
        .sdone      (sorter_sdone)
    );

    reg fifo_empty_d, fifo_empty_d2;
    always @(posedge rd_clk or posedge reset) begin
        if (reset) begin
            fifo_empty_d  <= 1'b1;
            fifo_empty_d2 <= 1'b1;
        end else begin
            fifo_empty_d2 <= fifo_empty_d;
            fifo_empty_d  <= fifo_empty;
        end
    end

    wire fifo_went_nonempty = (fifo_empty_d2 == 1'b1 && fifo_empty_d == 1'b0);

    reg [1:0] state;
    localparam S_IDLE  = 2'd0;
    localparam S_PULSE = 2'd1;
    localparam S_WAIT  = 2'd2;

    always @(posedge rd_clk or posedge reset) begin
        if (reset) begin
            state <= S_IDLE;
            rd_en <= 1'b0;
            sorter_data_valid <= 1'b0;
            sorter_data_in <= 64'b0;
            sort_out <= 64'b0;
            done <= 1'b0;
        end
        else begin
            rd_en <= 1'b0;
            sorter_data_valid <= 1'b0;
            done <= 1'b0;

            case (state)

                // --------------------------
                // INITIAL PUSH
                // --------------------------
                S_IDLE: begin
                    if (sorter_sdone && !fifo_empty) begin
                        rd_en <= 1'b1;
                        sorter_data_in <= fifo_out;
                        state <= S_PULSE;
                    end
                    else if (fifo_went_nonempty) begin
                        rd_en <= 1'b1;
                        sorter_data_in <= fifo_out;
                        state <= S_PULSE;
                    end
                end

                // Send data_valid to sorter
                S_PULSE: begin
                    rd_en <= 1'b0;
                    sorter_data_valid <= 1'b1;
                    state <= S_WAIT;
                end

                // Wait for sorter to finish
                S_WAIT: begin
                    if (sorter_sdone) begin
                        sort_out <= sorter_sorted;
                        done <= 1'b1;
                        state <= S_IDLE;
                    end
                    else state <= S_WAIT;
                end
            endcase
        end
    end

endmodule

Testing_folder/Testing_folder.srcs/sim_1/new/tb_top_rand_fifo_sort.v
`timescale 1ns / 1ps

module tb_top_rand_fifo_sort();

    reg wr_clk = 0;
    reg rd_clk = 0;
    reg reset = 1;

    wire [63:0] sort_out;
    wire        done;

    top_rand_fifo_sort uut (
        .wr_clk (wr_clk),
        .rd_clk (rd_clk),
        .reset  (reset),
        .sort_out(sort_out),
        .done    (done)
    );

    always #5 wr_clk = ~wr_clk;
    always #7 rd_clk = ~rd_clk;

    integer i;

    initial begin
        $dumpfile("tb_top_rand_fifo_sort.vcd");
        $dumpvars(0, tb_top_rand_fifo_sort);
        #1;
        reset = 1;
        #100;
        reset = 0;

        i = 0;
        while (1) begin
            @(posedge rd_clk);
            if (done) begin
                $display("%0t ns: SORTED = %h", $time, sort_out);
                i = i + 1;
                if (i == 8) begin
                    #20;
                    $finish;
                end
            end
        end

        #20;
        $finish;
    end

endmodule

Testing_folder/Testing_folder.sim/sim_1/behav/xsim/tb_top_rand_fifo_sort.vcd
$date
   Mon Nov 24 12:41:29 2025
$end

$version
  2024.2.0
  $dumpfile ("tb_top_rand_fifo_sort.vcd") 
$end

$timescale
  1ps
$end

$scope module tb_top_rand_fifo_sort $end
$var reg 1 ! wr_clk $end
$var reg 1 " rd_clk $end
$var reg 1 # reset $end
$var wire 64 $ sort_out [63:0] $end
$var wire 1 % done $end
$var integer 32 & i [31:0] $end
$scope module uut $end
$var wire 1 ' wr_clk $end
$var wire 1 ( rd_clk $end
$var wire 1 ) reset $end
$var reg 64 * sort_out [63:0] $end
$var reg 1 + done $end
$var reg 1 , rd_en $end
$var wire 64 - fifo_out [63:0] $end
$var wire 1 . fifo_empty $end
$var wire 1 / fifo_full $end
$var wire 1 0 drop $end
$var reg 64 1 sorter_data_in [63:0] $end
$var reg 1 2 sorter_data_valid $end
$var wire 64 3 sorter_sorted [63:0] $end
$var wire 1 4 sorter_sdone $end
$var reg 1 5 fifo_empty_d $end
$var reg 1 6 fifo_empty_d2 $end
$var wire 1 7 fifo_went_nonempty $end
$var reg 2 8 state [1:0] $end
$scope module u_top_random_fifo $end
$var wire 1 ' wr_clk $end
$var wire 1 ( rd_clk $end
$var wire 1 ) rst $end
$var wire 1 9 rd_en $end
$var wire 64 - fifo_dout [63:0] $end
$var wire 1 . fifo_empty $end
$var wire 1 / fifo_full $end
$var wire 1 0 drop $end
$var wire 64 : rnd64 [63:0] $end
$var wire 1 ; valid64 $end
$var reg 1 < wr_en $end
$var wire 64 = din [63:0] $end
$var reg 1 > drop_r $end
$scope module u_random $end
$var wire 1 ' clk $end
$var wire 1 ) rst $end
$var reg 64 ? rnd64 [63:0] $end
$var reg 1 @ valid64 $end
$var reg 8 A lfsr_byte [7:0] $end
$var wire 8 B lfsr_byte_next [7:0] $end
$var wire 1 C fb_byte $end
$var reg 8 D dlfsr [7:0] $end
$var wire 8 E dlfsr_next [7:0] $end
$var reg 5 F delay_val [4:0] $end
$var reg 3 G byte_index [2:0] $end
$var reg 5 H delay_cnt [4:0] $end
$var wire 1 I sample_enable $end
$upscope $end
$scope module u_fifo $end
$var wire 1 ' wr_clk $end
$var wire 1 ( rd_clk $end
$var wire 1 ) rst $end
$var wire 64 = din [63:0] $end
$var wire 1 J wr_en $end
$var wire 1 9 rd_en $end
$var wire 64 - dout [63:0] $end
$var wire 1 / full $end
$var wire 1 . empty $end
$var reg 4 K wr_ptr_bin [3:0] $end
$var reg 4 L wr_ptr_bin_next [3:0] $end
$var reg 4 M wr_ptr_gray [3:0] $end
$var reg 4 N wr_ptr_gray_next [3:0] $end
$var wire 3 O wr_addr [2:0] $end
$var reg 4 P rd_ptr_bin [3:0] $end
$var reg 4 Q rd_ptr_bin_next [3:0] $end
$var reg 4 R rd_ptr_gray [3:0] $end
$var reg 4 S rd_ptr_gray_next [3:0] $end
$var wire 3 T rd_addr [2:0] $end
$var reg 4 U rd_ptr_gray_sync1 [3:0] $end
$var reg 4 V rd_ptr_gray_sync2 [3:0] $end
$var reg 4 W wr_ptr_gray_sync1 [3:0] $end
$var reg 4 X wr_ptr_gray_sync2 [3:0] $end
$var wire 4 Y rd_ptr_bin_sync [3:0] $end
$var wire 4 Z wr_ptr_bin_sync [3:0] $end
$var reg 64 [ dout_reg [63:0] $end
$scope function gray_to_bin $end
$var reg 4 \ gray_to_bin [3:0] $end
$var reg 4 ] g [3:0] $end
$var integer 32 ^ i [31:0] $end
$upscope $end
$upscope $end
$upscope $end
$scope module u_insertion_sort $end
$var wire 1 ( clk $end
$var wire 1 ) rst $end
$var wire 1 _ data_valid $end
$var wire 64 ` data_in [63:0] $end
$var reg 64 a sorted [63:0] $end
$var reg 1 b sdone $end
$var reg 8 c key [7:0] $end
$var integer 32 d i [31:0] $end
$var integer 32 e j [31:0] $end
$var reg 3 f state [2:0] $end
$upscope $end
$upscope $end
$upscope $end
$enddefinitions $end

#0
$dumpvars
0!
0"
1#
b0 $
0%
bx &
0'
0(
1)
b0 *
0+
0,
bx -
1.
0/
00
b0 1
02
b0 3
04
15
16
07
b0 8
09
bx :
x;
0<
bx =
0>
bx ?
x@
bx A
bx B
xC
bx D
bx E
bx F
bx G
bx H
xI
0J
b0 K
b0 L
b0 M
b0 N
b0 O
b0 P
b0 Q
b0 R
b0 S
b0 T
b0 U
b0 V
b0 W
b0 X
b0 Y
b0 Z
bx [
b0 \
b0 ]
b11111111111111111111111111111111 ^
0_
b0 `
b0 a
0b
b0 c
b0 d
b0 e
b0 f
$end

#5000
1!
1'
b0 :
0;
b0 =
b0 ?
0@
b1 A
b10 B
0C
b10100101 D
b1001011 E
b100 F
b0 G
b1 H
0I

#7000
1"
1(

#10000
0!
0'

#14000
0"
0(

#15000
1!
1'

#20000
0!
0'

#21000
1"
1(

#25000
1!
1'

#28000
0"
0(

#30000
0!
0'

#35000
1!
1"
1'
1(

#40000
0!
0'

#42000
0"
0(

#45000
1!
1'

#49000
1"
1(

#50000
0!
0'

#55000
1!
1'

#56000
0"
0(

#60000
0!
0'

#63000
1"
1(

#65000
1!
1'

#70000
0!
0"
0'
0(

#75000
1!
1'

#77000
1"
1(

#80000
0!
0'

#84000
0"
0(

#85000
1!
1'

#90000
0!
0'

#91000
1"
1(

#95000
1!
1'

#98000
0"
0(

#100000
0!
0'

#101000
0#
b0 &
0)

#105000
1!
1"
1'
1(
b0 H
1I

#110000
0!
0'

#112000
0"
0(

#115000
1!
1'
b10 A
b100 B
b1001011 D
b10010111 E
b1111 F
b1 G
b11 H
0I

#119000
1"
1(

#120000
0!
0'

#125000
1!
1'
b10 H

#126000
0"
0(

#130000
0!
0'

#133000
1"
1(

#135000
1!
1'
b1 H

#140000
0!
0"
0'
0(

#145000
1!
1'
b0 H
1I

#147000
1"
1(

#150000
0!
0'

#154000
0"
0(

#155000
1!
1'
b100 A
b1000 B
b10010111 D
b101110 E
b1110 F
b10 G
b1110 H
0I

#160000
0!
0'

#161000
1"
1(

#165000
1!
1'
b1101 H

#168000
0"
0(

#170000
0!
0'

#175000
1!
1"
1'
1(
b1100 H

#180000
0!
0'

#182000
0"
0(

#185000
1!
1'
b1011 H

#189000
1"
1(

#190000
0!
0'

#195000
1!
1'
b1010 H

#196000
0"
0(

#200000
0!
0'

#203000
1"
1(

#205000
1!
1'
b1001 H

#210000
0!
0"
0'
0(

#215000
1!
1'
b1000 H

#217000
1"
1(

#220000
0!
0'

#224000
0"
0(

#225000
1!
1'
b111 H

#230000
0!
0'

#231000
1"
1(

#235000
1!
1'
b110 H

#238000
0"
0(

#240000
0!
0'

#245000
1!
1"
1'
1(
b101 H

#250000
0!
0'

#252000
0"
0(

#255000
1!
1'
b100 H

#259000
1"
1(

#260000
0!
0'

#265000
1!
1'
b11 H

#266000
0"
0(

#270000
0!
0'

#273000
1"
1(

#275000
1!
1'
b10 H

#280000
0!
0"
0'
0(

#285000
1!
1'
b1 H

#287000
1"
1(

#290000
0!
0'

#294000
0"
0(

#295000
1!
1'
b0 H
1I

#300000
0!
0'

#301000
1"
1(

#305000
1!
1'
b1000 A
b10001 B
1C
b101110 D
b1011101 E
b1100 F
b11 G
b1101 H
0I

#308000
0"
0(

#310000
0!
0'

#315000
1!
1"
1'
1(
b1100 H

#320000
0!
0'

#322000
0"
0(

#325000
1!
1'
b1011 H

#329000
1"
1(

#330000
0!
0'

#335000
1!
1'
b1010 H

#336000
0"
0(

#340000
0!
0'

#343000
1"
1(

#345000
1!
1'
b1001 H

#350000
0!
0"
0'
0(

#355000
1!
1'
b1000 H

#357000
1"
1(

#360000
0!
0'

#364000
0"
0(

#365000
1!
1'
b111 H

#370000
0!
0'

#371000
1"
1(

#375000
1!
1'
b110 H

#378000
0"
0(

#380000
0!
0'

#385000
1!
1"
1'
1(
b101 H

#390000
0!
0'

#392000
0"
0(

#395000
1!
1'
b100 H

#399000
1"
1(

#400000
0!
0'

#405000
1!
1'
b11 H

#406000
0"
0(

#410000
0!
0'

#413000
1"
1(

#415000
1!
1'
b10 H

#420000
0!
0"
0'
0(

#425000
1!
1'
b1 H

#427000
1"
1(

#430000
0!
0'

#434000
0"
0(

#435000
1!
1'
b0 H
1I

#440000
0!
0'

#441000
1"
1(

#445000
1!
1'
b10001 A
b100011 B
b1011101 D
b10111010 E
b1000 F
b100 G
b1011 H
0I

#448000
0"
0(

#450000
0!
0'

#455000
1!
1"
1'
1(
b1010 H

#460000
0!
0'

#462000
0"
0(

#465000
1!
1'
b1001 H

#469000
1"
1(

#470000
0!
0'

#475000
1!
1'
b1000 H

#476000
0"
0(

#480000
0!
0'

#483000
1"
1(

#485000
1!
1'
b111 H

#490000
0!
0"
0'
0(

#495000
1!
1'
b110 H

#497000
1"
1(

#500000
0!
0'

#504000
0"
0(

#505000
1!
1'
b101 H

#510000
0!
0'

#511000
1"
1(

#515000
1!
1'
b100 H

#518000
0"
0(

#520000
0!
0'

#525000
1!
1"
1'
1(
b11 H

#530000
0!
0'

#532000
0"
0(

#535000
1!
1'
b10 H

#539000
1"
1(

#540000
0!
0'

#545000
1!
1'
b1 H

#546000
0"
0(

#550000
0!
0'

#553000
1"
1(

#555000
1!
1'
b0 H
1I

#560000
0!
0"
0'
0(

#565000
1!
1'
b100011 A
b1000111 B
b10111010 D
b1110101 E
b1 F
b101 G
b111 H
0I

#567000
1"
1(

#570000
0!
0'

#574000
0"
0(

#575000
1!
1'
b110 H

#580000
0!
0'

#581000
1"
1(

#585000
1!
1'
b101 H

#588000
0"
0(

#590000
0!
0'

#595000
1!
1"
1'
1(
b100 H

#600000
0!
0'

#602000
0"
0(

#605000
1!
1'
b11 H

#609000
1"
1(

#610000
0!
0'

#615000
1!
1'
b10 H

#616000
0"
0(

#620000
0!
0'

#623000
1"
1(

#625000
1!
1'
b1 H

#630000
0!
0"
0'
0(

#635000
1!
1'
b0 H
1I

#637000
1"
1(

#640000
0!
0'

#644000
0"
0(

#645000
1!
1'
b1000111 A
b10001110 B
0C
b1110101 D
b11101010 E
b10 F
b110 G
b1 H
0I

#650000
0!
0'

#651000
1"
1(

#655000
1!
1'
b0 H
1I

#658000
0"
0(

#660000
0!
0'

#665000
1!
1"
1'
1(
b10001110 A
b11100 B
b11101010 D
b11010101 E
b100 F
b111 G
b1 H
0I

#670000
0!
0'

#672000
0"
0(

#675000
1!
1'
b0 H
1I

#679000
1"
1(

#680000
0!
0'

#685000
1!
1'
b1000111001000111001000110001000100001000000001000000001000000001 :
1;
b1000111001000111001000110001000100001000000001000000001000000001 =
b1000111001000111001000110001000100001000000001000000001000000001 ?
1@
b11100 A
b111000 B
b11010101 D
b10101010 E
b1000 F
b0 G
b11 H
0I

#686000
0"
0(

#690000
0!
0'

#693000
1"
1(

#695000
1!
1'
0;
1<
0@
b10 H
1J
b1 L
b1 N

#700000
0!
0"
0'
0(

#705000
1!
1'
0<
b1 H
0J
b1 K
b1 M
b1 O

#707000
1"
1(
b1 W

#710000
0!
0'

#714000
0"
0(

#715000
1!
1'
b0 H
1I

#720000
0!
0'

#721000
1"
1(
0.
b1 X
b1 Z
b1 \
b1 ]
b11111111111111111111111111111111 ^

#725000
1!
1'
b111000 A
b1110001 B
1C
b10101010 D
b1010101 E
b1 G
b111 H
0I

#728000
0"
0(

#730000
0!
0'

#735000
1!
1"
1'
1(
05
17
b110 H

#740000
0!
0'

#742000
0"
0(

#745000
1!
1'
b101 H

#749000
1"
1(
1,
bx 1
06
07
b1 8
19
b1 Q
b1 S
bx `

#750000
0!
0'

#755000
1!
1'
b100 H

#756000
0"
0(

#760000
0!
0'

#763000
1"
1(
0,
b1000111001000111001000110001000100001000000001000000001000000001 -
1.
12
b10 8
09
b1 P
b1 R
b1 T
b1000111001000111001000110001000100001000000001000000001000000001 [
1_

#765000
1!
1'
b11 H
b1 U

#770000
0!
0"
0'
0(

#775000
1!
1'
b10 H
b1 V
b1 Y
b11111111111111111111111111111111 ^

#777000
1"
1(
02
15
0_
b1 d
b10 f

#780000
0!
0'

#784000
0"
0(

#785000
1!
1'
b1 H

#790000
0!
0'

#791000
1"
1(
16
bx c
b11 f

#795000
1!
1'
b0 H
1I

#798000
0"
0(

#800000
0!
0'

#805000
1!
1"
1'
1(
b1110001 A
b11100010 B
0C
b1010101 D
b10101011 E
b10 G
b111 H
0I
b100 f

#810000
0!
0'

#812000
0"
0(

#815000
1!
1'
b110 H

#819000
1"
1(
b10 d
b10 f

#820000
0!
0'

#825000
1!
1'
b101 H

#826000
0"
0(

#830000
0!
0'

#833000
1"
1(
b1 e
b11 f

#835000
1!
1'
b100 H

#840000
0!
0"
0'
0(

#845000
1!
1'
b11 H

#847000
1"
1(
b100 f

#850000
0!
0'

#854000
0"
0(

#855000
1!
1'
b10 H

#860000
0!
0'

#861000
1"
1(
b11 d
b10 f

#865000
1!
1'
b1 H

#868000
0"
0(

#870000
0!
0'

#875000
1!
1"
1'
1(
b0 H
1I
b10 e
b11 f

#880000
0!
0'

#882000
0"
0(

#885000
1!
1'
b11100010 A
b11000100 B
b10101011 D
b1010111 E
b1 F
b11 G
b111 H
0I

#889000
1"
1(
b100 f

#890000
0!
0'

#895000
1!
1'
b110 H

#896000
0"
0(

#900000
0!
0'

#903000
1"
1(
b100 d
b10 f

#905000
1!
1'
b101 H

#910000
0!
0"
0'
0(

#915000
1!
1'
b100 H

#917000
1"
1(
b11 e
b11 f

#920000
0!
0'

#924000
0"
0(

#925000
1!
1'
b11 H

#930000
0!
0'

#931000
1"
1(
b100 f

#935000
1!
1'
b10 H

#938000
0"
0(

#940000
0!
0'

#945000
1!
1"
1'
1(
b1 H
b101 d
b10 f

#950000
0!
0'

#952000
0"
0(

#955000
1!
1'
b0 H
1I

#959000
1"
1(
b100 e
b11 f

#960000
0!
0'

#965000
1!
1'
b11000100 A
b10001001 B
1C
b1010111 D
b10101111 E
b10 F
b100 G
b1 H
0I

#966000
0"
0(

#970000
0!
0'

#973000
1"
1(
b100 f

#975000
1!
1'
b0 H
1I

#980000
0!
0"
0'
0(

#985000
1!
1'
b10001001 A
b10010 B
0C
b10101111 D
b1011110 E
b101 F
b101 G
b1 H
0I

#987000
1"
1(
b110 d
b10 f

#990000
0!
0'

#994000
0"
0(

#995000
1!
1'
b0 H
1I

#1000000
0!
0'

#1001000
1"
1(
b101 e
b11 f

#1005000
1!
1'
b10010 A
b100101 B
1C
b1011110 D
b10111100 E
b1011 F
b110 G
b100 H
0I

#1008000
0"
0(

#1010000
0!
0'

#1015000
1!
1"
1'
1(
b11 H
b100 f

#1020000
0!
0'

#1022000
0"
0(

#1025000
1!
1'
b10 H

#1029000
1"
1(
b111 d
b10 f

#1030000
0!
0'

#1035000
1!
1'
b1 H

#1036000
0"
0(

#1040000
0!
0'

#1043000
1"
1(
b110 e
b11 f

#1045000
1!
1'
b0 H
1I

#1050000
0!
0"
0'
0(

#1055000
1!
1'
b100101 A
b1001011 B
b10111100 D
b1111000 E
b111 F
b111 G
b1010 H
0I

#1057000
1"
1(
b100 f

#1060000
0!
0'

#1064000
0"
0(

#1065000
1!
1'
b1001 H

#1070000
0!
0'

#1071000
1"
1(
b1000 d
b10 f

#1075000
1!
1'
b1000 H

#1078000
0"
0(

#1080000
0!
0'

#1085000
1!
1"
1'
1(
b111 H
b101 f

#1090000
0!
0'

#1092000
0"
0(

#1095000
1!
1'
b110 H

#1099000
1"
1(
bx 3
14
bx a
1b
b1000 e
b0 f

#1100000
0!
0'

#1105000
1!
1'
b101 H

#1106000
0"
0(

#1110000
0!
0'

#1113000
1"
bx $
1%
1(
bx *
1+
04
b0 8
0b

#1115000
1!
1'
b100 H

#1120000
0!
0"
0'
0(

#1125000
1!
1'
b11 H

#1127000
1"
0%
b1 &
1(
0+

#1130000
0!
0'

#1134000
0"
0(

#1135000
1!
1'
b10 H

#1140000
0!
0'

#1141000
1"
1(

#1145000
1!
1'
b1 H

#1148000
0"
0(

#1150000
0!
0'

#1155000
1!
1"
1'
1(
b0 H
1I

#1160000
0!
0'

#1162000
0"
0(

#1165000
1!
1'
b10010100010010100010011100010011100010011100010011100000011100 :
1;
b10010100010010100010011100010011100010011100010011100000011100 =
b10010100010010100010011100010011100010011100010011100000011100 ?
1@
b1001011 A
b10010111 B
b1111000 D
b11110000 E
b1111 F
b0 G
b110 H
0I

#1169000
1"
1(

#1170000
0!
0'

#1175000
1!
1'
0;
1<
0@
b101 H
1J
b10 L
b11 N

#1176000
0"
0(

#1180000
0!
0'

#1183000
1"
1(

#1185000
1!
1'
0<
b100 H
0J
b10 K
b11 M
b10 O

#1190000
0!
0"
0'
0(

#1195000
1!
1'
b11 H

#1197000
1"
1(
b11 W

#1200000
0!
0'

#1204000
0"
0(

#1205000
1!
1'
b10 H

#1210000
0!
0'

#1211000
1"
1(
0.
b11 X
b10 Z
b10 \
b11 ]
b11111111111111111111111111111111 ^

#1215000
1!
1'
b1 H

#1218000
0"
0(

#1220000
0!
0'

