Asynchronous FIFO/Asynchronous FIFO.srcs/sources_1/new/async_fifo.v
`timescale 1ns / 1ps

module async_fifo #(
    parameter DATA_WIDTH = 64,
    parameter ADDR_WIDTH = 3
)(
    input  wire                   wr_clk,
    input  wire                   rd_clk,
    input  wire                   rst,
    input  wire [DATA_WIDTH-1:0]  din,
    input  wire                   wr_en,
    input  wire                   rd_en,
    output wire [DATA_WIDTH-1:0]  dout,
    output wire                   full,
    output wire                   empty
);

    localparam PTR_WIDTH = ADDR_WIDTH + 1;
    reg [DATA_WIDTH-1:0] mem [0:(1<<ADDR_WIDTH)-1];

    reg [PTR_WIDTH-1:0] wr_ptr_bin, wr_ptr_bin_next;
    reg [PTR_WIDTH-1:0] wr_ptr_gray, wr_ptr_gray_next;
    wire [ADDR_WIDTH-1:0] wr_addr = wr_ptr_bin[ADDR_WIDTH-1:0];

    reg [PTR_WIDTH-1:0] rd_ptr_bin, rd_ptr_bin_next;
    reg [PTR_WIDTH-1:0] rd_ptr_gray, rd_ptr_gray_next;
    wire [ADDR_WIDTH-1:0] rd_addr = rd_ptr_bin[ADDR_WIDTH-1:0];

    reg [PTR_WIDTH-1:0] rd_ptr_gray_sync1, rd_ptr_gray_sync2;
    always @(posedge wr_clk or posedge rst) begin
        if (rst) begin
            rd_ptr_gray_sync1 <= 0;
            rd_ptr_gray_sync2 <= 0;
        end else begin
            rd_ptr_gray_sync1 <= rd_ptr_gray;
            rd_ptr_gray_sync2 <= rd_ptr_gray_sync1;
        end
    end

    reg [PTR_WIDTH-1:0] wr_ptr_gray_sync1, wr_ptr_gray_sync2;
    always @(posedge rd_clk or posedge rst) begin
        if (rst) begin
            wr_ptr_gray_sync1 <= 0;
            wr_ptr_gray_sync2 <= 0;
        end else begin
            wr_ptr_gray_sync1 <= wr_ptr_gray;
            wr_ptr_gray_sync2 <= wr_ptr_gray_sync1;
        end
    end

    function [PTR_WIDTH-1:0] gray_to_bin;
        input [PTR_WIDTH-1:0] g;
        integer i;
        begin
            gray_to_bin[PTR_WIDTH-1] = g[PTR_WIDTH-1];
            for (i = PTR_WIDTH-2; i >= 0; i = i - 1)
                gray_to_bin[i] = gray_to_bin[i+1] ^ g[i];
        end
    endfunction

    wire [PTR_WIDTH-1:0] rd_ptr_bin_sync = gray_to_bin(rd_ptr_gray_sync2);
    assign full = (wr_ptr_gray_next == {~rd_ptr_gray_sync2[PTR_WIDTH-1:PTR_WIDTH-2], rd_ptr_gray_sync2[PTR_WIDTH-3:0]});

    wire [PTR_WIDTH-1:0] wr_ptr_bin_sync = gray_to_bin(wr_ptr_gray_sync2);
    assign empty = (rd_ptr_gray == wr_ptr_gray_sync2);

    always @(*) begin
        wr_ptr_bin_next = wr_ptr_bin;
        if (wr_en && !full)
            wr_ptr_bin_next = wr_ptr_bin + 1'b1;
        wr_ptr_gray_next = (wr_ptr_bin_next >> 1) ^ wr_ptr_bin_next;
    end

    always @(posedge wr_clk or posedge rst) begin
        if (rst) begin
            wr_ptr_bin <= 0;
            wr_ptr_gray <= 0;
        end else begin
            wr_ptr_bin <= wr_ptr_bin_next;
            wr_ptr_gray <= wr_ptr_gray_next;
        end
    end

    always @(posedge wr_clk) begin
        if (wr_en && !full)
            mem[wr_addr] <= din;
    end

    reg [DATA_WIDTH-1:0] dout_reg;
    always @(posedge rd_clk) begin
        if (rd_en && !empty)
            dout_reg <= mem[rd_addr];
    end
    assign dout = dout_reg;

    always @(*) begin
        rd_ptr_bin_next = rd_ptr_bin;
        if (rd_en && !empty)
            rd_ptr_bin_next = rd_ptr_bin + 1'b1;
        rd_ptr_gray_next = (rd_ptr_bin_next >> 1) ^ rd_ptr_bin_next;
    end

    always @(posedge rd_clk or posedge rst) begin
        if (rst) begin
            rd_ptr_bin <= 0;
            rd_ptr_gray <= 0;
        end else begin
            rd_ptr_bin <= rd_ptr_bin_next;
            rd_ptr_gray <= rd_ptr_gray_next;
        end
    end

endmodule

Random_num_generator/Random_num_generator.srcs/sources_1/new/random_gen.v
`timescale 1ns / 1ps

module random_gen(
    input  wire        clk,
    input  wire        rst,
    output reg  [63:0] rnd64,
    output reg         valid64
);

    reg  [7:0] lfsr_byte;
    wire [7:0] lfsr_byte_next;
    wire       fb_byte;
    assign fb_byte = lfsr_byte[7] ^ lfsr_byte[5] ^ lfsr_byte[4] ^ lfsr_byte[3];
    assign lfsr_byte_next = { lfsr_byte[6:0], fb_byte };

    reg  [7:0] dlfsr;
    wire [7:0] dlfsr_next;
    assign dlfsr_next = { dlfsr[6:0], dlfsr[7] ^ dlfsr[5] ^ dlfsr[3] ^ dlfsr[2] };

    reg  [4:0] delay_val;
    reg [7:0] byte_array [0:6];
    reg [2:0] byte_index;
    reg [4:0] delay_cnt;

    wire sample_enable = (delay_cnt == 5'd0);

    always @(posedge clk) begin
        if (rst) begin
            lfsr_byte <= 8'h01;
            dlfsr     <= 8'hA5;
            delay_val <= 5'd4;
        end
        else begin
            if (sample_enable) begin
                dlfsr <= dlfsr_next;
                lfsr_byte <= lfsr_byte_next;
                if ((dlfsr_next[3:0] ^ dlfsr_next[7:4]) == 4'd0)
                    delay_val <= 5'd8;
                else
                    delay_val <= {1'b0, (dlfsr_next[3:0] ^ dlfsr_next[7:4])};
            end
        end
    end

    always @(posedge clk) begin
        if (rst) begin
            byte_index <= 3'd0;
            delay_cnt  <= 5'd1;
            rnd64      <= 64'd0;
            valid64    <= 1'b0;
        end
        else begin
            valid64 <= 1'b0;
            if (delay_cnt == 5'd0) begin
                if (byte_index == 3'd7) begin
                    rnd64 <= {
                        lfsr_byte,
                        byte_array[6],
                        byte_array[5],
                        byte_array[4],
                        byte_array[3],
                        byte_array[2],
                        byte_array[1],
                        byte_array[0]
                    };
                    valid64 <= 1'b1;
                    byte_index <= 3'd0;
                end
                else begin
                    byte_array[byte_index] <= lfsr_byte;
                    byte_index <= byte_index + 3'd1;
                end

                if (delay_val < 2)
                    delay_cnt <= 5'd1;
                else
                    delay_cnt <= delay_val - 5'd1;
            end
            else begin
                delay_cnt <= delay_cnt - 5'd1;
            end
        end
    end

endmodule

Testing_folder/Testing_folder.srcs/sources_1/new/top_random_fifo.v
`timescale 1ns / 1ps

module top_random_fifo (
    input  wire        wr_clk,
    input  wire        rd_clk,
    input  wire        rst,
    input  wire        rd_en,
    output wire [63:0] fifo_dout,
    output wire        fifo_empty,
    output wire        fifo_full,
    output wire        drop
);

    wire [63:0] rnd64;
    wire        valid64;
    reg         wr_en;
    wire [63:0] din;
    reg         drop_r;

    random_gen u_random (
        .clk(wr_clk),
        .rst(rst),
        .rnd64(rnd64),
        .valid64(valid64)
    );

    assign din = rnd64;

    always @(posedge wr_clk or posedge rst) begin
        if (rst) begin
            wr_en <= 1'b0;
            drop_r <= 1'b0;
        end
        else begin
            drop_r <= 1'b0;
            if (valid64) begin
                if (!fifo_full) begin
                    wr_en <= 1'b1;
                end
                else begin
                    wr_en <= 1'b0;
                    drop_r <= 1'b1;
                end
            end
            else begin
                wr_en <= 1'b0;
            end
        end
    end

    async_fifo #(
        .DATA_WIDTH(64),
        .ADDR_WIDTH(3)
    ) u_fifo (
        .wr_clk(wr_clk),
        .rd_clk(rd_clk),
        .rst(rst),
        .din(din),
        .wr_en(wr_en),
        .rd_en(rd_en),
        .dout(fifo_dout),
        .full(fifo_full),
        .empty(fifo_empty)
    );

    assign drop = drop_r;

endmodule

Testing_folder/Testing_folder.srcs/sources_1/new/tb_top_random_fifo.v
`timescale 1ns/1ps
module tb_top_random_fifo;

    reg wr_clk;
    reg rd_clk;
    reg rst;

    wire [63:0] fifo_dout;
    reg  rd_en;
    wire fifo_empty;
    wire fifo_full;
    wire drop;

    integer cycle_count;

    top_random_fifo dut (
        .wr_clk(wr_clk),
        .rd_clk(rd_clk),
        .rst(rst),
        .rd_en(rd_en),
        .fifo_dout(fifo_dout),
        .fifo_empty(fifo_empty),
        .fifo_full(fifo_full),
        .drop(drop)
    );

    initial wr_clk = 0;
    always #7 wr_clk = ~wr_clk;

    initial rd_clk = 0;
    always #5 rd_clk = ~rd_clk;

    task do_reset;
    begin
        rst = 1;
        rd_en = 0;
        cycle_count = 0;
        repeat (10) @(posedge wr_clk);
        rst = 0;
    end
    endtask

    initial begin
        $dumpfile("wave.vcd");
        $dumpvars(0, tb_top_random_fifo);

        do_reset;

        while (cycle_count < 5000) begin   // <-- Simulation limit
            @(posedge rd_clk);
            cycle_count = cycle_count + 1;

            if (!fifo_empty)
                rd_en = 1;
            else
                rd_en = 0;
        end

        $display("Simulation complete.");
        $finish;
    end

    always @(posedge rd_clk) begin
        if (rd_en && !fifo_empty)
            $display("T=%0t  READ: %016h", $time, fifo_dout);
    end

    always @(posedge wr_clk) begin
        if (drop)
            $display("T=%0t  FIFO FULL → DROP", $time);
    end

endmodule

Testing_folder/Testing_folder.sim/sim_1/behav/xsim/wave.vcd
$date
   Sun Nov 23 13:42:21 2025
$end

$version
  2024.2.0
  $dumpfile ("wave.vcd") 
$end

$timescale
  1ps
$end

$scope module tb_top_random_fifo $end
$var reg 1 ! wr_clk $end
$var reg 1 " rd_clk $end
$var reg 1 # rst $end
$var wire 64 $ fifo_dout [63:0] $end
$var reg 1 % rd_en $end
$var wire 1 & fifo_empty $end
$var wire 1 ' fifo_full $end
$var wire 1 ( drop $end
$var integer 32 ) cycle_count [31:0] $end
$scope module dut $end
$var wire 1 * wr_clk $end
$var wire 1 + rd_clk $end
$var wire 1 , rst $end
$var wire 1 - rd_en $end
$var wire 64 $ fifo_dout [63:0] $end
$var wire 1 & fifo_empty $end
$var wire 1 ' fifo_full $end
$var wire 1 ( drop $end
$var wire 64 . rnd64 [63:0] $end
$var wire 1 / valid64 $end
$var reg 1 0 wr_en $end
$var wire 64 1 din [63:0] $end
$var reg 1 2 drop_r $end
$scope module u_random $end
$var wire 1 * clk $end
$var wire 1 , rst $end
$var reg 64 3 rnd64 [63:0] $end
$var reg 1 4 valid64 $end
$var reg 8 5 lfsr_byte [7:0] $end
$var wire 8 6 lfsr_byte_next [7:0] $end
$var wire 1 7 fb_byte $end
$var reg 8 8 dlfsr [7:0] $end
$var wire 8 9 dlfsr_next [7:0] $end
$var reg 5 : delay_val [4:0] $end
$var reg 3 ; byte_index [2:0] $end
$var reg 5 < delay_cnt [4:0] $end
$var wire 1 = sample_enable $end
$upscope $end
$scope module u_fifo $end
$var wire 1 * wr_clk $end
$var wire 1 + rd_clk $end
$var wire 1 , rst $end
$var wire 64 1 din [63:0] $end
$var wire 1 > wr_en $end
$var wire 1 - rd_en $end
$var wire 64 $ dout [63:0] $end
$var wire 1 ' full $end
$var wire 1 & empty $end
$var reg 9 ? wr_ptr_bin [8:0] $end
$var reg 9 @ wr_ptr_bin_next [8:0] $end
$var reg 9 A wr_ptr_gray [8:0] $end
$var reg 9 B wr_ptr_gray_next [8:0] $end
$var wire 8 C wr_addr [7:0] $end
$var reg 9 D rd_ptr_bin [8:0] $end
$var reg 9 E rd_ptr_bin_next [8:0] $end
$var reg 9 F rd_ptr_gray [8:0] $end
$var reg 9 G rd_ptr_gray_next [8:0] $end
$var wire 8 H rd_addr [7:0] $end
$var reg 9 I rd_ptr_gray_sync1 [8:0] $end
$var reg 9 J rd_ptr_gray_sync2 [8:0] $end
$var reg 9 K wr_ptr_gray_sync1 [8:0] $end
$var reg 9 L wr_ptr_gray_sync2 [8:0] $end
$var wire 9 M rd_ptr_bin_sync [8:0] $end
$var wire 9 N wr_ptr_bin_sync [8:0] $end
$var reg 64 O dout_reg [63:0] $end
$scope function gray_to_bin $end
$var reg 9 P gray_to_bin [8:0] $end
$var reg 9 Q g [8:0] $end
$var integer 32 R i [31:0] $end
$upscope $end
$upscope $end
$upscope $end
$scope task do_reset $end
$upscope $end
$upscope $end
$enddefinitions $end

#0
$dumpvars
0!
0"
1#
bx $
0%
1&
0'
0(
b0 )
0*
0+
1,
0-
bx .
x/
00
bx 1
02
bx 3
x4
bx 5
bx 6
x7
bx 8
bx 9
bx :
bx ;
bx <
x=
0>
b0 ?
b0 @
b0 A
b0 B
b0 C
b0 D
b0 E
b0 F
b0 G
b0 H
b0 I
b0 J
b0 K
b0 L
b0 M
b0 N
bx O
b0 P
b0 Q
b11111111111111111111111111111111 R
$end

#5000
1"
1+

#7000
1!
1*
b0 .
0/
b0 1
b0 3
04
b1 5
b10 6
07
b10100101 8
b1001011 9
b100 :
b0 ;
b1 <
0=

#10000
0"
0+

#14000
0!
0*

#15000
1"
1+

#20000
0"
0+

#21000
1!
1*

#25000
1"
1+

#28000
0!
0*

#30000
0"
0+

#35000
1!
1"
1*
1+

#40000
0"
0+

#42000
0!
0*

#45000
1"
1+

#49000
1!
1*

#50000
0"
0+

#55000
1"
1+

#56000
0!
0*

#60000
0"
0+

#63000
1!
1*

#65000
1"
1+

#70000
0!
0"
0*
0+

#75000
1"
1+

#77000
1!
1*

#80000
0"
0+

#84000
0!
0*

#85000
1"
1+

#90000
0"
0+

#91000
1!
1*

#95000
1"
1+

#98000
0!
0*

#100000
0"
0+

#105000
1!
1"
1*
1+

#110000
0"
0+

#112000
0!
0*

#115000
1"
1+

#119000
1!
1*

#120000
0"
0+

#125000
1"
1+

#126000
0!
0*

#130000
0"
0+

#133000
1!
0#
1*
0,
b0 <
1=

#135000
1"
b1 )
1+

#140000
0!
0"
0*
0+

#145000
1"
b10 )
1+

#147000
1!
1*
b10 5
b100 6
b1001011 8
b10010111 9
b1111 :
b1 ;
b11 <
0=

#150000
0"
0+

#154000
0!
0*

#155000
1"
b11 )
1+

#160000
0"
0+

#161000
1!
1*
b10 <

#165000
1"
b100 )
1+

#168000
0!
0*

#170000
0"
0+

#175000
1!
1"
b101 )
1*
1+
b1 <

#180000
0"
0+

#182000
0!
0*

#185000
1"
b110 )
1+

#189000
1!
1*
b0 <
1=

#190000
0"
0+

#195000
1"
b111 )
1+

#196000
0!
0*

#200000
0"
0+

#203000
1!
1*
b100 5
b1000 6
b10010111 8
b101110 9
b1110 :
b10 ;
b1110 <
0=

#205000
1"
b1000 )
1+

#210000
0!
0"
0*
0+

#215000
1"
b1001 )
1+

#217000
1!
1*
b1101 <

#220000
0"
0+

#224000
0!
0*

#225000
1"
b1010 )
1+

#230000
0"
0+

#231000
1!
1*
b1100 <

#235000
1"
b1011 )
1+

#238000
0!
0*

#240000
0"
0+

#245000
1!
1"
b1100 )
1*
1+
b1011 <

#250000
0"
0+

#252000
0!
0*

#255000
1"
b1101 )
1+

#259000
1!
1*
b1010 <

#260000
0"
0+

#265000
1"
b1110 )
1+

#266000
0!
0*

#270000
0"
0+

#273000
1!
1*
b1001 <

#275000
1"
b1111 )
1+

#280000
0!
0"
0*
0+

#285000
1"
b10000 )
1+

#287000
1!
1*
b1000 <

#290000
0"
0+

#294000
0!
0*

#295000
1"
b10001 )
1+

#300000
0"
0+

#301000
1!
1*
b111 <

#305000
1"
b10010 )
1+

#308000
0!
0*

#310000
0"
0+

#315000
1!
1"
b10011 )
1*
1+
b110 <

#320000
0"
0+

#322000
0!
0*

#325000
1"
b10100 )
1+

#329000
1!
1*
b101 <

#330000
0"
0+

#335000
1"
b10101 )
1+

#336000
0!
0*

#340000
0"
0+

#343000
1!
1*
b100 <

#345000
1"
b10110 )
1+

#350000
0!
0"
0*
0+

#355000
1"
b10111 )
1+

#357000
1!
1*
b11 <

#360000
0"
0+

#364000
0!
0*

#365000
1"
b11000 )
1+

#370000
0"
0+

#371000
1!
1*
b10 <

#375000
1"
b11001 )
1+

#378000
0!
0*

#380000
0"
0+

#385000
1!
1"
b11010 )
1*
1+
b1 <

#390000
0"
0+

#392000
0!
0*

#395000
1"
b11011 )
1+

#399000
1!
1*
b0 <
1=

#400000
0"
0+

#405000
1"
b11100 )
1+

#406000
0!
0*

#410000
0"
0+

#413000
1!
1*
b1000 5
b10001 6
17
b101110 8
b1011101 9
b1100 :
b11 ;
b1101 <
0=

#415000
1"
b11101 )
1+

#420000
0!
0"
0*
0+

#425000
1"
b11110 )
1+

#427000
1!
1*
b1100 <

#430000
0"
0+

#434000
0!
0*

#435000
1"
b11111 )
1+

#440000
0"
0+

#441000
1!
1*
b1011 <

#445000
1"
b100000 )
1+

#448000
0!
0*

#450000
0"
0+

#455000
1!
1"
b100001 )
1*
1+
b1010 <

#460000
0"
0+

#462000
0!
0*

#465000
1"
b100010 )
1+

#469000
1!
1*
b1001 <

#470000
0"
0+

#475000
1"
b100011 )
1+

#476000
0!
0*

#480000
0"
0+

#483000
1!
1*
b1000 <

#485000
1"
b100100 )
1+

#490000
0!
0"
0*
0+

#495000
1"
b100101 )
1+

#497000
1!
1*
b111 <

#500000
0"
0+

#504000
0!
0*

#505000
1"
b100110 )
1+

#510000
0"
0+

#511000
1!
1*
b110 <

#515000
1"
b100111 )
1+

#518000
0!
0*

#520000
0"
0+

#525000
1!
1"
b101000 )
1*
1+
b101 <

#530000
0"
0+

#532000
0!
0*

#535000
1"
b101001 )
1+

#539000
1!
1*
b100 <

#540000
0"
0+

#545000
1"
b101010 )
1+

#546000
0!
0*

#550000
0"
0+

#553000
1!
1*
b11 <

#555000
1"
b101011 )
1+

#560000
0!
0"
0*
0+

#565000
1"
b101100 )
1+

#567000
1!
1*
b10 <

#570000
0"
0+

#574000
0!
0*

#575000
1"
b101101 )
1+

#580000
0"
0+

#581000
1!
1*
b1 <

#585000
1"
b101110 )
1+

#588000
0!
0*

#590000
0"
0+

#595000
1!
1"
b101111 )
1*
1+
b0 <
1=

#600000
0"
0+

#602000
0!
0*

#605000
1"
b110000 )
1+

#609000
1!
1*
b10001 5
b100011 6
b1011101 8
b10111010 9
b1000 :
b100 ;
b1011 <
0=

#610000
0"
0+

#615000
1"
b110001 )
1+

#616000
0!
0*

#620000
0"
0+

#623000
1!
1*
b1010 <

#625000
1"
b110010 )
1+

#630000
0!
0"
0*
0+

#635000
1"
b110011 )
1+

#637000
1!
1*
b1001 <

#640000
0"
0+

#644000
0!
0*

#645000
1"
b110100 )
1+

#650000
0"
0+

#651000
1!
1*
b1000 <

#655000
1"
b110101 )
1+

#658000
0!
0*

#660000
0"
0+

#665000
1!
1"
b110110 )
1*
1+
b111 <

#670000
0"
0+

#672000
0!
0*

#675000
1"
b110111 )
1+

#679000
1!
1*
b110 <

#680000
0"
0+

#685000
1"
b111000 )
1+

#686000
0!
0*

#690000
0"
0+

#693000
1!
1*
b101 <

#695000
1"
b111001 )
1+

#700000
0!
0"
0*
0+

#705000
1"
b111010 )
1+

#707000
1!
1*
b100 <

#710000
0"
0+

#714000
0!
0*

#715000
1"
b111011 )
1+

#720000
0"
0+

#721000
1!
1*
b11 <

#725000
1"
b111100 )
1+

#728000
0!
0*

#730000
0"
0+

#735000
1!
1"
b111101 )
1*
1+
b10 <

#740000
0"
0+

#742000
0!
0*

#745000
1"
b111110 )
1+

#749000
1!
1*
b1 <

#750000
0"
0+

#755000
1"
b111111 )
1+

#756000
0!
0*

#760000
0"
0+

#763000
1!
1*
b0 <
1=

#765000
1"
b1000000 )
1+

#770000
0!
0"
0*
0+

#775000
1"
b1000001 )
1+

#777000
1!
1*
b100011 5
b1000111 6
b10111010 8
b1110101 9
b1 :
b101 ;
b111 <
0=

#780000
0"
0+

#784000
0!
0*

#785000
1"
b1000010 )
1+

#790000
0"
0+

#791000
1!
1*
b110 <

#795000
1"
b1000011 )
1+

#798000
0!
0*

#800000
0"
0+

#805000
1!
1"
b1000100 )
1*
1+
b101 <

#810000
0"
0+

#812000
0!
0*

#815000
1"
b1000101 )
1+

#819000
1!
1*
b100 <

#820000
0"
0+

#825000
1"
b1000110 )
1+

#826000
0!
0*

#830000
0"
0+

#833000
1!
1*
b11 <

#835000
1"
b1000111 )
1+

#840000
0!
0"
0*
0+

#845000
1"
b1001000 )
1+

#847000
1!
1*
b10 <

#850000
0"
0+

#854000
0!
0*

#855000
1"
b1001001 )
1+

#860000
0"
0+

#861000
1!
1*
b1 <

#865000
1"
b1001010 )
1+

#868000
0!
0*

#870000
0"
0+

#875000
1!
1"
b1001011 )
1*
1+
b0 <
1=

#880000
0"
0+

#882000
0!
0*

#885000
1"
b1001100 )
1+

#889000
1!
1*
b1000111 5
b10001110 6
07
b1110101 8
b11101010 9
b10 :
b110 ;
b1 <
0=

#890000
0"
0+

#895000
1"
b1001101 )
1+

#896000
0!
0*

#900000
0"
0+

#903000
1!
1*
b0 <
1=

#905000
1"
b1001110 )
1+

#910000
0!
0"
0*
0+

#915000
1"
b1001111 )
1+

#917000
1!
1*
b10001110 5
b11100 6
b11101010 8
b11010101 9
b100 :
b111 ;
b1 <
0=

#920000
0"
0+

#924000
0!
0*

#925000
1"
b1010000 )
1+

#930000
0"
0+

#931000
1!
1*
b0 <
1=

#935000
1"
b1010001 )
1+

#938000
0!
0*

#940000
0"
0+

#945000
1!
1"
b1010010 )
1*
1+
b1000111001000111001000110001000100001000000001000000001000000001 .
1/
b1000111001000111001000110001000100001000000001000000001000000001 1
b1000111001000111001000110001000100001000000001000000001000000001 3
14
b11100 5
b111000 6
b11010101 8
b10101010 9
b1000 :
b0 ;
b11 <
0=

#950000
0"
0+

#952000
0!
0*

#955000
1"
b1010011 )
1+

#959000
1!
1*
0/
10
04
b10 <
1>
b1 @
b1 B

#960000
0"
0+

#965000
1"
b1010100 )
1+

#966000
0!
0*

#970000
0"
0+

#973000
1!
1*
00
b1 <
0>
b1 ?
b1 A
b1 C

#975000
1"
b1010101 )
1+
b1 K

#980000
0!
0"
0*
0+

#985000
1"
0&
b1010110 )
1+
b1 L
b1 N
b1 P
b1 Q
b11111111111111111111111111111111 R

#987000
1!
1*
b0 <
1=

#990000
0"
0+

#994000
0!
0*

#995000
1"
b1000111001000111001000110001000100001000000001000000001000000001 $
1%
b1010111 )
1+
1-
b1 E
b1 G
b1000111001000111001000110001000100001000000001000000001000000001 O

#1000000
0"
0+

#1001000
1!
1*
b111000 5
b1110001 6
17
b10101010 8
b1010101 9
b1 ;
b111 <
0=

#1005000
1"
1&
b1011000 )
1+
b1 D
b1 F
b1 H

#1008000
0!
0*

#1010000
0"
0+

#1015000
1!
1"
0%
b1011001 )
1*
1+
0-
b110 <
b1 I

#1020000
0"
0+

#1022000
0!
0*

#1025000
1"
b1011010 )
1+

#1029000
1!
1*
b101 <
b1 J
b1 M
b11111111111111111111111111111111 R

#1030000
0"
0+

#1035000
1"
b1011011 )
1+

#1036000
0!
0*

#1040000
0"
0+

#1043000
1!
1*
b100 <

#1045000
1"
b1011100 )
1+

#1050000
0!
0"
0*
0+

#1055000
1"
b1011101 )
1+

#1057000
1!
1*
b11 <

#1060000
0"
0+

#1064000
0!
0*

#1065000
1"
b1011110 )
1+

#1070000
0"
0+

#1071000
1!
1*
b10 <

#1075000
1"
b1011111 )
1+

#1078000
0!
0*

#1080000
0"
0+

#1085000
1!
1"
b1100000 )
1*
1+
b1 <

#1090000
0"
0+

#1092000
0!
0*

#1095000
1"
b1100001 )
1+

#1099000
1!
1*
b0 <
1=

#1100000
0"
0+

#1105000
1"
b1100010 )
1+

#1106000
0!
0*

#1110000
0"
0+

#1113000
1!
1*
b1110001 5
b11100010 6
07
b1010101 8
b10101011 9
b10 ;
b111 <
0=

#1115000
1"
b1100011 )
1+

#1120000
0!
0"
0*
0+

#1125000
1"
b1100100 )
1+

#1127000
1!
1*
b110 <

#1130000
0"
0+

#1134000
0!
0*

#1135000
1"
b1100101 )
1+

#1140000
0"
0+

#1141000
1!
1*
b101 <

#1145000
1"
b1100110 )
1+

#1148000
0!
0*

#1150000
0"
0+

#1155000
1!
1"
b1100111 )
1*
1+
b100 <

#1160000
0"
0+

#1162000
0!
0*

#1165000
1"
b1101000 )
1+

#1169000
1!
1*
b11 <

#1170000
0"
0+

#1175000
1"
b1101001 )
1+

#1176000
0!
0*

#1180000
0"
0+

#1183000
1!
1*
b10 <

#1185000
1"
b1101010 )
1+

#1190000
0!
0"
0*
0+

#1195000
1"
b1101011 )
1+

#1197000
1!
1*
b1 <

#1200000
0"
0+

#1204000
0!
0*

#1205000
1"
b1101100 )
1+

#1210000
0"
0+

#1211000
1!
1*
b0 <
1=

#1215000
1"
b1101101 )
1+

#1218000
0!
0*

#1220000
0"
0+

#1225000
1!
1"
b1101110 )
1*
1+
b11100010 5
b11000100 6
b10101011 8
b1010111 9
b1 :
b11 ;
b111 <
0=

#1230000
0"
0+

#1232000
0!
0*

#1235000
1"
b1101111 )
1+

#1239000
1!
1*
b110 <

#1240000
0"
0+

#1245000
1"
b1110000 )
1+

#1246000
0!
0*

#1250000
0"
0+

#1253000
1!
1*
b101 <

#1255000
1"
b1110001 )
1+

#1260000
0!
0"
0*
0+

#1265000
1"
b1110010 )
1+

#1267000
1!
1*
b100 <

#1270000
0"
0+

#1274000
0!
0*

#1275000
1"
b1110011 )
1+

#1280000
0"
0+

#1281000
1!
1*
b11 <

#1285000
1"
b1110100 )
1+

#1288000
0!
0*

#1290000
0"
0+

#1295000
1!
1"
b1110101 )
1*
1+
b10 <

#1300000
0"
0+

#1302000
0!
0*

#1305000
1"
b1110110 )
1+

#1309000
1!
1*
b1 <

#1310000
0"
0+

#1315000
1"
b1110111 )
1+

#1316000
0!
0*

#1320000
0"
0+

#1323000
1!
1*
b0 <
1=

#1325000
1"
b1111000 )
1+

#1330000
0!
0"
0*
0+

#1335000
1"
b1111001 )
1+

#1337000
1!
1*
b11000100 5
b10001001 6
17
b1010111 8
b10101111 9
b10 :
b100 ;
b1 <
0=

#1340000
0"
0+

#1344000
0!
0*

#1345000
1"
b1111010 )
1+

#1350000
0"
0+

#1351000
1!
1*
b0 <
1=

#1355000
1"
b1111011 )
1+

#1358000
0!
0*

#1360000
0"
0+

#1365000
1!
1"
b1111100 )
1*
1+
b10001001 5
b10010 6
07
b10101111 8
b1011110 9
b101 :
b101 ;
b1 <
0=

#1370000
0"
0+

#1372000
0!
0*

#1375000
1"
b1111101 )
1+

#1379000
1!
1*
b0 <
1=

#1380000
0"
0+

#1385000
1"
b1111110 )
1+

#1386000
0!
0*

#1390000
0"
0+

#1393000
1!
1*
b10010 5
b100101 6
17
b1011110 8
b10111100 9
b1011 :
b110 ;
b100 <
0=

#1395000
1"
b1111111 )
1+

#1400000
0!
0"
0*
0+

#1405000
1"
b10000000 )
1+

#1407000
1!
1*
b11 <

#1410000
0"
0+

#1414000
0!
0*

#1415000
1"
b10000001 )
1+

#1420000
0"
0+

#1421000
1!
1*
b10 <

#1425000
1"
b10000010 )
1+

#1428000
0!
0*

#1430000
0"
0+

#1435000
1!
1"
b10000011 )
1*
1+
b1 <

#1440000
0"
0+

#1442000
0!
0*

#1445000
1"
b10000100 )
1+

#1449000
1!
1*
b0 <
1=

#1450000
0"
0+

#1455000
1"
b10000101 )
1+

#1456000
0!
0*

#1460000
0"
0+

#1463000
1!
1*
b100101 5
b1001011 6
b10111100 8
b1111000 9
b111 :
b111 ;
b1010 <
0=

#1465000
1"
b10000110 )
1+

#1470000
0!
0"
0*
0+

#1475000
1"
b10000111 )
1+

#1477000
1!
1*
b1001 <

#1480000
0"
0+

#1484000
0!
0*

#1485000
1"
b10001000 )
1+

#1490000
0"
0+

#1491000
1!
1*
b1000 <

#1495000
1"
b10001001 )
1+

#1498000
0!
0*

#1500000
0"
0+

#1505000
1!
1"
b10001010 )
1*
1+
b111 <

#1510000
0"
0+

#1512000
0!
0*

#1515000
1"
b10001011 )
1+

#1519000
1!
1*
b110 <

#1520000
0"
0+

#1525000
1"
b10001100 )
1+

#1526000
0!
0*

#1530000
0"
0+

#1533000
1!
1*
b101 <

#1535000
1"
b10001101 )
1+

#1540000
0!
0"
0*
0+

#1545000
1"
b10001110 )
1+

#1547000
1!
1*
b100 <

#1550000
0"
0+

#1554000
0!
0*

#1555000
1"
b10001111 )
1+

#1560000
0"
0+

#1561000
1!
1*
b11 <

#1565000
1"
b10010000 )
1+

#1568000
0!
0*

#1570000
0"
0+

#1575000
1!
1"
b10010001 )
1*
1+
b10 <

#1580000
0"
0+

#1582000
0!
0*

#1585000
1"
b10010010 )
1+

#1589000
1!
1*
b1 <

#1590000
0"
0+

#1595000
1"
b10010011 )
1+

#1596000
0!
0*

#1600000
0"
0+

#1603000
1!
1*
b0 <
1=

#1605000
1"
b10010100 )
1+

#1610000
0!
0"
0*
0+

#1615000
1"
b10010101 )
1+

#1617000
1!
1*
b10010100010010100010011100010011100010011100010011100000011100 .
1/
b10010100010010100010011100010011100010011100010011100000011100 1
b10010100010010100010011100010011100010011100010011100000011100 3
14
b1001011 5
b10010111 6
b1111000 8
b11110000 9
b1111 :
b0 ;
b110 <
0=

#1620000
0"
0+

#1624000
0!
0*

#1625000
1"
b10010110 )
1+

#1630000
0"
0+

#1631000
1!
1*
0/
10
04
b101 <
1>
b10 @
b11 B

#1635000
1"
b10010111 )
1+

#1638000
0!
0*

#1640000
0"
0+

#1645000
1!
1"
b10011000 )
1*
1+
00
b100 <
0>
b10 ?
b11 A
b10 C

#1650000
0"
0+

#1652000
0!
0*

#1655000
1"
b10011001 )
1+
b11 K

#1659000
1!
1*
b11 <

#1660000
0"
0+

#1665000
1"
0&
b10011010 )
1+
b11 L
b10 N
b10 P
b11 Q
b11111111111111111111111111111111 R

#1666000
0!
0*

#1670000
0"
0+

#1673000
1!
1*
b10 <

#1675000
1"
b10010100010010100010011100010011100010011100010011100000011100 $
1%
b10011011 )
1+
1-
b10 E
b11 G
b10010100010010100010011100010011100010011100010011100000011100 O

#1680000
0!
0"
0*
0+

#1685000
1"
1&
b10011100 )
1+
b10 D
b11 F
b10 H

#1687000
1!
1*
b1 <
b11 I

#1690000
0"
0+

#1694000
0!
0*

#1695000
1"
0%
b10011101 )
1+
0-

#1700000
0"
0+

